dialoghook/__init__.py
dialoghook/common.py
dialoghook/request.py
dialoghook/response.py
dialoghook-0.1.2.dist-info/WHEEL
dialoghook-0.1.2.dist-info/METADATA
dialoghook-0.1.2.dist-info/RECORD
